mycalc/calculator.py
shbak_calc-0.0.1.dist-info/METADATA
shbak_calc-0.0.1.dist-info/WHEEL
shbak_calc-0.0.1.dist-info/top_level.txt
shbak_calc-0.0.1.dist-info/RECORD
