Metadata-Version: 2.1
Name: shbak-calc
Version: 0.0.1
Summary: oss-dev my calculator 0001
Home-page: 
Download-URL: 
Author: shbak
License: UNKNOWN
Platform: UNKNOWN
Classifier: Programming Language :: Python :: 3
